icekit_events/__init__.py
icekit_events/admin.py
icekit_events/admin_forms.py
icekit_events/apps.py
icekit_events/appsettings.py
icekit_events/forms.py
icekit_events/icekit_events_plugins.py
icekit_events/models.py
icekit_events/urls.py
icekit_events/validators.py
icekit_events/views.py
icekit_events/management/__init__.py
icekit_events/management/commands/__init__.py
icekit_events/management/commands/create_event_occurrences.py
icekit_events/migrations/0001_initial.py
icekit_events/migrations/0002_auto_20150605_1418.py
icekit_events/migrations/0003_auto_20150607_2314.py
icekit_events/migrations/0004_auto_20150607_2336.py
icekit_events/migrations/0005_auto_20151015_0540.py
icekit_events/migrations/0006_auto_20151015_0542.py
icekit_events/migrations/0007_auto_20151207_1221.py
icekit_events/migrations/0008_auto_20151208_2213.py
icekit_events/migrations/0009_auto_20160117_1752.py
icekit_events/migrations/0010_auto_20160203_1856.py
icekit_events/migrations/0011_event_show_in_calendar.py
icekit_events/migrations/0012_auto_20160706_1606.py
icekit_events/migrations/0013_auto_20160809_1215.py
icekit_events/migrations/0014_auto_20160810_1036.py
icekit_events/migrations/0015_auto_20160929_1308.py
icekit_events/migrations/0016_auto_20160929_1504.py
icekit_events/migrations/0017_eventpage.py
icekit_events/migrations/0018_auto_20160929_2106.py
icekit_events/migrations/__init__.py
icekit_events/plugins/__init__.py
icekit_events/sample_data/__init__.py
icekit_events/sample_data/apps.py
icekit_events/sample_data/models.py
icekit_events/sample_data/migrations/0001_initial.py
icekit_events/sample_data/migrations/__init__.py
icekit_events/static/admin/js/event_all_day_field.js
icekit_events/static/icekit_events/bower.json
icekit_events/static/icekit_events/bower_components/font-awesome/.bower.json
icekit_events/static/icekit_events/bower_components/font-awesome/.gitignore
icekit_events-0.7.dist-info/DESCRIPTION.rst
icekit_events-0.7.dist-info/METADATA
icekit_events-0.7.dist-info/RECORD
icekit_events-0.7.dist-info/WHEEL
icekit_events-0.7.dist-info/metadata.json
icekit_events-0.7.dist-info/top_level.txt
